einsteinpy_geodesics/__init__.py
einsteinpy_geodesics/geodesics_wrapper.py
einsteinpy_geodesics/utils.py
einsteinpy_geodesics/julia_backend/KerrSolver.jl
einsteinpy_geodesics/julia_backend/run.jl
einsteinpy_geodesics-0.1.0.dist-info/COPYING
einsteinpy_geodesics-0.1.0.dist-info/WHEEL
einsteinpy_geodesics-0.1.0.dist-info/METADATA
einsteinpy_geodesics-0.1.0.dist-info/RECORD
