Metadata-Version: 2.1
Name: einsteinpy_geodesics
Version: 0.1.0
Summary: ====================
Home-page: https://github.com/einsteinpy/einsteinpy-geodesics
License: UNKNOWN
Keywords: aero,aerospace,engineering,astrodynamics,orbits,kepler,orbital mechanics
Author: Shreyas Bapat
Author-email: bapat.shreyas@gmail.com
Requires-Python: >=3.7,<3.9
Classifier: License :: OSI Approved :: MIT License
Classifier: Development Status :: 4 - Beta
Classifier: Intended Audience :: Education
Classifier: Intended Audience :: Science/Research
Classifier: License :: OSI Approved :: MIT License
Classifier: Operating System :: OS Independent
Classifier: Programming Language :: Python
Classifier: Programming Language :: Python :: 3
Classifier: Programming Language :: Python :: 3.7
Classifier: Programming Language :: Python :: 3.8
Classifier: Topic :: Scientific/Engineering
Classifier: Topic :: Scientific/Engineering :: Physics
Classifier: Topic :: Scientific/Engineering :: Astronomy
Requires-Dist: numpy
Requires-Dist: black ; extra == "dev"
Requires-Dist: coverage ; extra == "dev"
Requires-Dist: hypothesis ; extra == "dev"
Requires-Dist: isort ; extra == "dev"
Requires-Dist: mypy>=0.740 ; extra == "dev"
Requires-Dist: pycodestyle ; extra == "dev"
Requires-Dist: pytest>=3.2 ; extra == "dev"
Requires-Dist: pytest-cov<2.6.0 ; extra == "dev"
Requires-Dist: pytest-doctestplus ; extra == "dev"
Requires-Dist: pytest-mpl ; extra == "dev"
Requires-Dist: pytest-mypy ; extra == "dev"
Requires-Dist: pytest-remotedata ; extra == "dev"
Requires-Dist: sphinx ; extra == "dev"
Requires-Dist: alabaster ; extra == "dev"
Requires-Dist: tox ; extra == "dev"
Project-URL: Source, https://github.com/einsteinpy/einsteinpy-geodesics
Project-URL: Tracker, https://github.com/einsteinpy/einsteinpy-geodesics/issues
Provides-Extra: dev
